pygeoquery/__init__.py
pygeoquery/geo_collection_reference.py
pygeoquery-0.1.0.dist-info/LICENSE
pygeoquery-0.1.0.dist-info/METADATA
pygeoquery-0.1.0.dist-info/WHEEL
pygeoquery-0.1.0.dist-info/top_level.txt
pygeoquery-0.1.0.dist-info/RECORD
