Metadata-Version: 2.1
Name: pygeoquery
Version: 0.1.0
Summary: Geoqueries on Firestore Database for Python
Home-page: https://github.com/booncol/pygeoquery
Author: Lukasz Majda
Author-email: lukasz.majda@gmail.com
License: MIT
Keywords: firestore geoquery geospatial geofire geohash
Requires-Python: >=3.9
License-File: LICENSE
Requires-Dist: geohashr (==1.3.1)
Requires-Dist: geopy (==2.4.0)
Requires-Dist: google-cloud-firestore (==2.13.0)
